devenv_cli/__init__.py
devenv_cli/__main__.py
devenv_cli/main.py
devenv_cli-0.1.4.dist-info/METADATA
devenv_cli-0.1.4.dist-info/WHEEL
devenv_cli-0.1.4.dist-info/entry_points.txt
devenv_cli-0.1.4.dist-info/RECORD
