Metadata-Version: 2.3
Name: devenv-cli
Version: 0.1.4
Summary: 
Author: Shuchir Jain
Author-email: pip@shuchir.dev
Requires-Python: >=3.10,<4.0
Classifier: Programming Language :: Python :: 3
Classifier: Programming Language :: Python :: 3.10
Classifier: Programming Language :: Python :: 3.11
Classifier: Programming Language :: Python :: 3.12
Classifier: Programming Language :: Python :: 3.13
Requires-Dist: docker (>=7.1.0,<8.0.0)
Requires-Dist: questionary (>=2.1.0,<3.0.0)
Requires-Dist: typer (>=0.16.0,<0.17.0)
Requires-Dist: yaspin (>=3.1.0,<4.0.0)
